LICENSE
MANIFEST.in
README.md
requirements.txt
requirements_dev.txt
setup.py
nappy/__init__.py
nappy/nappy_api.py
nappy.egg-info/PKG-INFO
nappy.egg-info/SOURCES.txt
nappy.egg-info/dependency_links.txt
nappy.egg-info/entry_points.txt
nappy.egg-info/not-zip-safe
nappy.egg-info/requires.txt
nappy.egg-info/top_level.txt
nappy/config/annotations.ini
nappy/config/local_attributes.ini
nappy/config/nappy.ini
nappy/na_file/__init__.py
nappy/na_file/na_core.py
nappy/na_file/na_file.py
nappy/na_file/na_file_1001.py
nappy/na_file/na_file_1010.py
nappy/na_file/na_file_1020.py
nappy/na_file/na_file_2010.py
nappy/na_file/na_file_2110.py
nappy/na_file/na_file_2160.py
nappy/na_file/na_file_2310.py
nappy/na_file/na_file_3010.py
nappy/na_file/na_file_4010.py
nappy/nc_interface/__init__.py
nappy/nc_interface/na_content_collector.py
nappy/nc_interface/na_to_nc.py
nappy/nc_interface/na_to_xarray.py
nappy/nc_interface/nc_to_na.py
nappy/nc_interface/xarray_objs_to_na_files.py
nappy/nc_interface/xarray_to_na.py
nappy/nc_interface/xarray_utils.py
nappy/script/__init__.py
nappy/script/na2nc.py
nappy/script/nc2csv.py
nappy/script/nc2na.py
nappy/utils/__init__.py
nappy/utils/common_utils.py
nappy/utils/compare.py
nappy/utils/compare_na.py
nappy/utils/ffi_translator.py
nappy/utils/list_manipulator.py
nappy/utils/parse_config.py
nappy/utils/right_strip.py
nappy/utils/text_parser.py
tests/__init__.py
tests/common.py
tests/conftest.py
tests/quick_tests_na_to_nc.py
tests/quick_tests_nc_to_na.py
tests/run_cmd_line_tests.py
tests/test_1010_to_1020.py
tests/test_2010_to_2110.py
tests/test_2010_to_2310.py
tests/test_na2nc.py
tests/test_na_file.py
tests/test_na_file_1001.py
tests/test_nc2csv.py
tests/test_nc2na.py
tests/test_parse_config.py
tests/test_var_units.py
tests/test_xarray_utils.py