Metadata-Version: 2.1
Name: nappy
Version: 2.0.2
Summary: NASA Ames Processing in Python
Home-page: https://github.com/cedadev/nappy
Author: Ag Stephens
Author-email: ag.stephens@stfc.ac.uk
License: BSD 3-Clause License
Keywords: Python CSV NASA Ames NetCDF convert xarray
Platform: all
Classifier: Development Status :: 4 - Beta
Classifier: Environment :: Console
Classifier: Intended Audience :: Developers
Classifier: Intended Audience :: Science/Research
Classifier: License :: OSI Approved :: BSD License
Classifier: Operating System :: OS Independent
Classifier: Programming Language :: Python
Provides-Extra: netcdf_conversion
License-File: LICENSE
